omniserver/__init__.py
omniserver/certs.py
omniserver/clients.py
omniserver/core.py
omniserver/servers.py
omniserver/version.py
omniserver-1.1.0.dist-info/LICENSE
omniserver-1.1.0.dist-info/METADATA
omniserver-1.1.0.dist-info/WHEEL
omniserver-1.1.0.dist-info/top_level.txt
omniserver-1.1.0.dist-info/RECORD
