Metadata-Version: 2.1
Name: omniserver
Version: 1.1.0
Summary: Module for network testing and prototyping
Home-page: https://github.com/LLCZ00/Omniserver
Author: LLCZ00
License: Apache 2.0
Keywords: malware analysis networking
Classifier: Development Status :: 5 - Production/Stable
Classifier: Intended Audience :: Information Technology
Classifier: Intended Audience :: Developers
Classifier: License :: OSI Approved :: Apache Software License
Classifier: Natural Language :: English
Classifier: Programming Language :: Python :: 3
Classifier: Operating System :: OS Independent
Classifier: Topic :: Security
Classifier: Topic :: Utilities
Requires-Python: >=3.8
License-File: LICENSE
Requires-Dist: dnslib
